{
	"__mysql__": {
		"auto_primary": false,
		"create": ["_created", "account", "date", "time", "type", "ip"],
		"db": "mems",
		"host": "primary",
		"indexes": {
			"account": null
		},
		"primary": null,
		"table": "patient_activity"
	},

	"__name__": "Patient_Activity",

	"_created": {
		"__type__": "timestamp",
		"__optional__": true,
		"__sql__": {
			"opts": "default CURRENT_TIMESTAMP"
		}
	},

	"account": {
		"__type__": "uuid"
	},

	"date": {
		"__type__": "date"
	},

	"time": {
		"__type__": "time"
	},

	"type": {
		"__type__": "string",
		"__options__": ["signin", "signout"]
	},

	"ip": {
		"__type__": "ip"
	}
}
